ppf/datamatrix/__init__.py
ppf/datamatrix/codec_C40.py
ppf/datamatrix/codec_X12.py
ppf/datamatrix/codec_ascii.py
ppf/datamatrix/codec_common.py
ppf/datamatrix/codec_edifact.py
ppf/datamatrix/codec_text.py
ppf/datamatrix/datamatrix.py
ppf/datamatrix/utils.py
ppf_datamatrix-0.2.dist-info/LICENSE
ppf_datamatrix-0.2.dist-info/METADATA
ppf_datamatrix-0.2.dist-info/WHEEL
ppf_datamatrix-0.2.dist-info/top_level.txt
ppf_datamatrix-0.2.dist-info/RECORD
