Metadata-Version: 2.1
Name: ppf-datamatrix
Version: 0.2
Summary: Python port of https://github.com/datalog/datamatrix-svg
Home-page: https://github.com/adrianschlatter/ppf.datamatrix/tree/master
Author: Adrian Schlatter
License: MIT
Keywords: datamatrix,svg,python,ipython,codecs
Classifier: Development Status :: 4 - Beta
Classifier: Intended Audience :: Developers
Classifier: Intended Audience :: Manufacturing
Classifier: Intended Audience :: Information Technology
Classifier: Intended Audience :: Other Audience
Classifier: Topic :: Utilities
Classifier: License :: OSI Approved :: MIT License
Classifier: Programming Language :: Python :: 3
Classifier: Operating System :: OS Independent
Classifier: Framework :: IPython
Requires-Python: >=3.6
License-File: LICENSE
Provides-Extra: dev
Requires-Dist: tox ; extra == 'dev'
Requires-Dist: twine ; extra == 'dev'
Provides-Extra: test
Requires-Dist: flake8 ; extra == 'test'
Requires-Dist: check-manifest ; extra == 'test'
Requires-Dist: pytest ; extra == 'test'
Requires-Dist: coverage ; extra == 'test'
